cdci_data_analysis/__init__.py
cdci_data_analysis/app_logging.py
cdci_data_analysis/configurer.py
cdci_data_analysis/pkg_info.json
cdci_data_analysis/pytest_fixtures.py
cdci_data_analysis/analysis/__init__.py
cdci_data_analysis/analysis/catalog.py
cdci_data_analysis/analysis/drupal_helper.py
cdci_data_analysis/analysis/email_helper.py
cdci_data_analysis/analysis/exceptions.py
cdci_data_analysis/analysis/hash.py
cdci_data_analysis/analysis/instrument.py
cdci_data_analysis/analysis/io_helper.py
cdci_data_analysis/analysis/job_manager.py
cdci_data_analysis/analysis/json.py
cdci_data_analysis/analysis/parameters.py
cdci_data_analysis/analysis/plot_tools.py
cdci_data_analysis/analysis/products.py
cdci_data_analysis/analysis/queries.py
cdci_data_analysis/analysis/renku_helper.py
cdci_data_analysis/analysis/tokenHelper.py
cdci_data_analysis/config_dir/conf_env.yml.example
cdci_data_analysis/config_dir/gunicorn.conf
cdci_data_analysis/flask_app/__init__.py
cdci_data_analysis/flask_app/app.py
cdci_data_analysis/flask_app/dispatcher_query.py
cdci_data_analysis/flask_app/logstash.py
cdci_data_analysis/flask_app/mock_data_server.py
cdci_data_analysis/flask_app/mock_worker.py
cdci_data_analysis/flask_app/schemas.py
cdci_data_analysis/flask_app/tasks.py
cdci_data_analysis/flask_app/static/style.css
cdci_data_analysis/flask_app/static/js/addInput.js
cdci_data_analysis/flask_app/templates/_formhelpers.html
cdci_data_analysis/flask_app/templates/analysis_display_app.html
cdci_data_analysis/flask_app/templates/body_article_product_gallery.py
cdci_data_analysis/flask_app/templates/bokeh_embed.html
cdci_data_analysis/flask_app/templates/email.html
cdci_data_analysis/flask_app/templates/incident_report_email.html
cdci_data_analysis/flask_app/templates/__pycache__/body_article_product_gallery.cpython-38.pyc
cdci_data_analysis/flask_app/templates/__pycache__/body_article_product_gallery.cpython-39.pyc
cdci_data_analysis/old_stuff/__init__.py
cdci_data_analysis/old_stuff/analysis.py
cdci_data_analysis-1.3.3.dist-info/LICENSE.rst
cdci_data_analysis-1.3.3.dist-info/METADATA
cdci_data_analysis-1.3.3.dist-info/WHEEL
cdci_data_analysis-1.3.3.dist-info/top_level.txt
cdci_data_analysis-1.3.3.dist-info/RECORD
